setup.cfg
setup.py
it_library/__init__.py
it_library.egg-info/PKG-INFO
it_library.egg-info/SOURCES.txt
it_library.egg-info/dependency_links.txt
it_library.egg-info/entry_points.txt
it_library.egg-info/top_level.txt
it_library.egg-info/zip-safe