Metadata-Version: 1.0
Name: it-library
Version: 0.0.1dev
Summary: common functions for IT projects
Home-page: spicevan.com
Author: Fenton Travers
Author-email: fenton.travers@gmail.com
License: GPLv2
Keywords: git
Platform: UNKNOWN
